vocmax/ASHRAE2017_temperature_data.csv
vocmax/__init__.py
vocmax/bifacial.py
vocmax/main.py
vocmax/mins01_nsrdb_ashrae_comparison.pkl
vocmax/nsrdb.py
vocmax/nsrdb_ashrae_comparison.pkl
vocmax-1.0.1.dist-info/LICENSE
vocmax-1.0.1.dist-info/METADATA
vocmax-1.0.1.dist-info/WHEEL
vocmax-1.0.1.dist-info/top_level.txt
vocmax-1.0.1.dist-info/RECORD
