Metadata-Version: 2.1
Name: vocmax
Version: 1.0.1
Summary: Calculate the maximum module open circuit voltage to find the maximum solar PV string length
Home-page: https://github.com/toddkarin/vocmax
Author: toddkarin
Author-email: pvtools.lbl@gmail.com
License: UNKNOWN
Platform: UNKNOWN
Classifier: Programming Language :: Python :: 3
Classifier: License :: OSI Approved :: MIT License
Classifier: Operating System :: OS Independent
Requires-Dist: numpy
Requires-Dist: pandas
Requires-Dist: pvlib
Requires-Dist: matplotlib
Requires-Dist: tqdm
Requires-Dist: pvfactors
